confo/Confo.py
confo/__init__.py
confo/Backends/AbstractBackend.py
confo/Backends/FileBackend.py
confo/Backends/ZookeeperBackend.py
confo/Backends/__init__.py
confo/Exceptions/__init__.py
confo2-0.1.1.dist-info/LICENSE
confo2-0.1.1.dist-info/METADATA
confo2-0.1.1.dist-info/WHEEL
confo2-0.1.1.dist-info/top_level.txt
confo2-0.1.1.dist-info/RECORD
