Metadata-Version: 2.1
Name: confo2
Version: 0.1.1
Summary: Confo is a configuration manager, built to support multiple backend systems
Home-page: https://github.com/sambe-consulting/confo
Author: Sambe Consulting
Author-email: development@sambe.co.za
License: Apache License 2.0
Classifier: License :: OSI Approved :: Apache Software License
Classifier: Programming Language :: Python :: 3
Requires-Python: >=3.6
License-File: LICENSE
Requires-Dist: kazoo==2.10.0
Requires-Dist: singleton-decorator==1.0.0
